NodeWikiBook/README.md
NodeWikiBook/__init__.py
NodeWikiBook/__main__.py
NodeWikiBook/file.epub
NodeWikiBook/index.html
NodeWikiBook/css/__init__.py
NodeWikiBook/css/annotations.css
NodeWikiBook/css/main.css
NodeWikiBook/css/normalize.css
NodeWikiBook/css/popup.css
NodeWikiBook/font/__init__.py
NodeWikiBook/font/fontello.eot
NodeWikiBook/font/fontello.svg
NodeWikiBook/font/fontello.ttf
NodeWikiBook/font/fontello.woff
NodeWikiBook/img/__init__.py
NodeWikiBook/img/annotator-glyph-sprite.png
NodeWikiBook/img/annotator-icon-sprite.png
NodeWikiBook/img/apple-touch-icon.png
NodeWikiBook/img/cancelfullscreen.png
NodeWikiBook/img/close.png
NodeWikiBook/img/fullscreen.png
NodeWikiBook/img/loader.gif
NodeWikiBook/img/menu-icon.png
NodeWikiBook/img/save.png
NodeWikiBook/img/saved.png
NodeWikiBook/img/settings-s.png
NodeWikiBook/img/settings.png
NodeWikiBook/img/star.png
NodeWikiBook/js/__init__.py
NodeWikiBook/js/epub.js
NodeWikiBook/js/epub.min.js
NodeWikiBook/js/epub.min.map
NodeWikiBook/js/hooks.min.js
NodeWikiBook/js/hooks.min.map
NodeWikiBook/js/reader.js
NodeWikiBook/js/reader.js.map
NodeWikiBook/js/reader.min.js
NodeWikiBook/js/reader.min.map
NodeWikiBook/js/hooks/__init__.py
NodeWikiBook/js/hooks/extensions/__init__.py
NodeWikiBook/js/hooks/extensions/highlight.js
NodeWikiBook/js/libs/__init__.py
NodeWikiBook/js/libs/jquery.min.js
NodeWikiBook/js/libs/localforage.min.js
NodeWikiBook/js/libs/screenfull.js
NodeWikiBook/js/libs/screenfull.min.js
NodeWikiBook/js/libs/zip.min.js
NodeWikiBook/js/plugins/__init__.py
NodeWikiBook/js/plugins/hypothesis.js
NodeWikiBook/js/plugins/search.js
node_wiki_book-2024.3.1.0.dist-info/METADATA
node_wiki_book-2024.3.1.0.dist-info/WHEEL
node_wiki_book-2024.3.1.0.dist-info/entry_points.txt
node_wiki_book-2024.3.1.0.dist-info/top_level.txt
node_wiki_book-2024.3.1.0.dist-info/RECORD
